{
	"backtrace" : 0,
	"backtraceGraph" : 
	{
		"commands" : [],
		"files" : 
		[
			"Executable/CMakeLists.txt"
		],
		"nodes" : 
		[
			{
				"file" : 0
			}
		]
	},
	"dependencies" : 
	[
		{
			"backtrace" : 0,
			"id" : "SearchEngineLib::@6890427a1f51a3e7e1df"
		}
	],
	"folder" : 
	{
		"name" : "QtInternalTargets"
	},
	"id" : "Executable_autogen_timestamp_deps::@a203b219dd3218d60f25",
	"isGeneratorProvided" : true,
	"name" : "Executable_autogen_timestamp_deps",
	"paths" : 
	{
		"build" : "Executable",
		"source" : "Executable"
	},
	"sources" : [],
	"type" : "UTILITY"
}
